Workbook

Sheet Dashboard
A1: 📊 TABLEAU DE BORD FINANCIER
A2: Mise à jour: 20/01/2026
A4: 💰 INDICATEURS CLÉS
A5: Salaire Mensuel | B5: =Revenus!F4
A6: Dépenses Fixes | B6: ="Dépenses Fixes"!B10
A7: Épargne Totale/Mois | B7: =4000
A8: Investissement/Mois | B8: =1000
A10: 📈 RÉPARTITION DU SALAIRE
A11: Catégorie | B11: Montant | C11: % du Salaire
A12: Dépenses Fixes | B12: ="Dépenses Fixes"!B10 | C12: ="Dépenses Fixes"!B10/14000
A13: Épargne Personnelle | B13: 2000 | C13: =2000/14000
A14: Épargne Famille | B14: 2000 | C14: =2000/14000
A15: Investissements | B15: 1000 | C15: =1000/14000
A16: Reste à Vivre | B16: =14000-"Dépenses Fixes"!B10-2000-2000-1000 | C16: =(14000-"Dépenses Fixes"!B10-2000-2000-1000)/14000
A17: TOTAL | B17: 14000 | C17: 1
A20: 💎 PATRIMOINE & OBJECTIFS | E20: 📝 NOTES & CONSEILS
A21: Patrimoine Total Actuel | B21: ="Patrimoine Global"!E6 | E21: ✓ Taux d'épargne excellent (28.5%)
A22: Épargne Personnelle Cumulée | B22: =Épargne!E8 | E22: ✓ Objectif: 6 mois d'épargne d'urgence
A23: Épargne Famille Totale | B23: =Épargne!C24 | E23: • Diversifier les investissements
A24: Valeur Portefeuille Bourse | B24: ="Investissements Bourse"!H15 | E24: • Suivre mensuellement les performances
A25: Performance Bourse | B25: ="Investissements Bourse"!J15 | E25: • Réajuster le budget si nécessaire
A27: 🎯 TAUX D'ÉPARGNE
A28: Taux d'épargne actuel: | B28: =4000/14000
A29: Objectif: 28.5% ✓ ATTEINT!
A30: Mois d'épargne d'urgence disponibles: | B30: =Épargne!E8/Revenus!C4

Sheet Revenus
A1: SUIVI DES REVENUS
A3: Mois | B3: Année | C3: Salaire Net | D3: Primes/Bonus | E3: Autres Revenus | F3: TOTAL
A4: Janvier | B4: 2025 | C4: 14000 | D4: 0 | E4: 0 | F4: =C4+D4+E4
A5: Février | B5: 2025 | C5: 14000 | D5: 0 | E5: 0 | F5: =C5+D5+E5
A6: Mars | B6: 2025 | C6: 14000 | D6: 0 | E6: 0 | F6: =C6+D6+E6
A7: Avril | B7: 2025 | F7: =C7+D7+E7
A8: Mai | B8: 2025 | F8: =C8+D8+E8
A9: Juin | B9: 2025 | F9: =C9+D9+E9
A10: Juillet | B10: 2025 | F10: =C10+D10+E10
A11: Août | B11: 2025 | F11: =C11+D11+E11
A12: Septembre | B12: 2025 | F12: =C12+D12+E12
A13: Octobre | B13: 2025 | F13: =C13+D13+E13
A14: Novembre | B14: 2025 | F14: =C14+D14+E14
A15: Décembre | B15: 2025 | F15: =C15+D15+E15
A16: TOTAL ANNUEL | C16: =SUM(C4:C15) | D16: =SUM(D4:D15) | E16: =SUM(E4:E15) | F16: =SUM(F4:F15)
A17: MOYENNE MENSUELLE | C17: =AVERAGE(C4:C15) | D17: =AVERAGE(D4:D15) | E17: =AVERAGE(E4:E15) | F17: =AVERAGE(F4:F15)

Sheet Dépenses Fixes
A1: DÉPENSES FIXES MENSUELLES
A3: Catégorie | B3: Montant Prévu | C3: Montant Réel | D3: Statut | E3: Écart
A4: Loyer | B4: 2250 | C4: 2250 | D4: Payé | E4: =C4-B4
A5: Électricité | B5: 200 | C5: 200 | D5: Payé | E5: =C5-B5
A6: Eau | B6: 250 | C6: 250 | D6: Payé | E6: =C6-B6
A7: Internet | B7: 45 | C7: 45 | D7: Payé | E7: =C7-B7
A8: Téléphone | B8: 30 | C8: 30 | D8: Payé | E8: =C8-B8
A9: Autre | B9: 20 | C9: 20 | D9: Payé | E9: =C9-B9
A10: TOTAL | B10: =SUM(B4:B9) | C10: =SUM(C4:C9) | E10: =SUM(E4:E9)
A12: HISTORIQUE MENSUEL
A13: Mois | B13: Total Dépenses | C13: Budget | D13: Écart | E13: % du Salaire | F13: Commentaires
A14: Janvier 2025 | B14: 2795 | C14: 2795 | D14: =B14-C14 | E14: =B14/14000
A15: Février 2025 | B15: 2795 | C15: 2795 | D15: =B15-C15 | E15: =B15/14000
A16: Mars 2025 | B16: 2795 | C16: 2795 | D16: =B16-C16 | E16: =B16/14000

Sheet Dépenses Variables
A1: DÉPENSES VARIABLES
A2: Budget disponible: ~6 205 MAD/mois (Reste à vivre)
A4: Catégorie | B4: Budget Prévu | C4: Dépensé | D4: Écart | E4: % Budget | F4: Statut
A5: Alimentation | B5: 2500 | C5: 0 | D5: =B5-C5 | E5: =C5/B5 | F5: =IF(E5>1,"⚠️ Dépassement","✓ OK")
A6: Transport | B6: 800 | C6: 0 | D6: =B6-C6 | E6: =C6/B6 | F6: =IF(E6>1,"⚠️ Dépassement","✓ OK")
A7: Loisirs | B7: 600 | C7: 0 | D7: =B7-C7 | E7: =C7/B7 | F7: =IF(E7>1,"⚠️ Dépassement","✓ OK")
A8: Santé | B8: 300 | C8: 0 | D8: =B8-C8 | E8: =C8/B8 | F8: =IF(E8>1,"⚠️ Dépassement","✓ OK")
A9: Vêtements | B9: 200 | C9: 0 | D9: =B9-C9 | E9: =C9/B9 | F9: =IF(E9>1,"⚠️ Dépassement","✓ OK")
A10: Imprévus | B10: 500 | C10: 0 | D10: =B10-C10 | E10: =C10/B10 | F10: =IF(E10>1,"⚠️ Dépassement","✓ OK")
A11: Autres | B11: 1305 | C11: 0 | D11: =B11-C11 | E11: =C11/B11 | F11: =IF(E11>1,"⚠️ Dépassement","✓ OK")
A12: TOTAL | B12: =SUM(B5:B11) | C12: =SUM(C5:C11) | D12: =SUM(D5:D11)
A15: DÉTAILS DES DÉPENSES DU MOIS
A16: Date | B16: Catégorie | C16: Description | D16: Montant | E16: Mode de paiement

Sheet Épargne
A1: SUIVI DE L'ÉPARGNE
A3: 💰 ÉPARGNE PERSONNELLE
A4: Objectif: Fonds d'urgence de 6 mois = 84,000 MAD
A5: Mois | B5: Versement | C5: Retraits | D5: Net | E5: Solde Cumulé | F5: Progression Objectif
A6: Janvier 2025 | B6: 2000 | C6: 0 | D6: =B6-C6 | E6: 2000 | F6: =E6/84000
A7: Février 2025 | B7: 2000 | C7: 0 | D7: =B7-C7 | E7: 4000 | F7: =E7/84000
A8: Mars 2025 | B8: 2000 | C8: 0 | D8: =B8-C8 | E8: 6000 | F8: =E8/84000
A9: Mois 4 | B9: 2000 | C9: 0 | D9: =B9-C9 | E9: =E8+D9 | F9: =E9/84000
A10: Mois 5 | B10: 2000 | C10: 0 | D10: =B10-C10 | E10: =E9+D10 | F10: =E10/84000
A11: Mois 6 | B11: 2000 | C11: 0 | D11: =B11-C11 | E11: =E10+D11 | F11: =E11/84000
A12: Mois 7 | B12: 2000 | C12: 0 | D12: =B12-C12 | E12: =E11+D12 | F12: =E12/84000
A13: Mois 8 | B13: 2000 | C13: 0 | D13: =B13-C13 | E13: =E12+D13 | F13: =E13/84000
A14: Mois 9 | B14: 2000 | C14: 0 | D14: =B14-C14 | E14: =E13+D14 | F14: =E14/84000
A15: Mois 10 | B15: 2000 | C15: 0 | D15: =B15-C15 | E15: =E14+D15 | F15: =E15/84000
A16: Mois 11 | B16: 2000 | C16: 0 | D16: =B16-C16 | E16: =E15+D16 | F16: =E16/84000
A17: Mois 12 | B17: 2000 | C17: 0 | D17: =B17-C17 | E17: =E16+D17 | F17: =E17/84000
A20: 👨‍👩‍👧‍👦 ÉPARGNE FAMILLE / PARENTS
A21: Mois | B21: Versement | C21: Total Versé | D21: Notes | E21: Statut
A22: Janvier 2025 | B22: 2000 | C22: 2000 | E22: Versé
A23: Février 2025 | B23: 2000 | C23: 4000 | E23: Versé
A24: Mars 2025 | B24: 2000 | C24: 6000 | E24: Versé
A25: Mois 4 | B25: 2000 | C25: =C24+B25
A26: Mois 5 | B26: 2000 | C26: =C25+B26
A27: Mois 6 | B27: 2000 | C27: =C26+B27
A28: Mois 7 | B28: 2000 | C28: =C27+B28
A29: Mois 8 | B29: 2000 | C29: =C28+B29
A30: Mois 9 | B30: 2000 | C30: =C29+B30
A31: Mois 10 | B31: 2000 | C31: =C30+B31
A32: Mois 11 | B32: 2000 | C32: =C31+B32
A33: Mois 12 | B33: 2000 | C33: =C32+B33
A36: 📊 RÉSUMÉ ÉPARGNE TOTALE
A37: Épargne mensuelle totale: | B37: 4000
A38: Taux d'épargne (% du salaire): | B38: =0.2857142857142857

Sheet Investissements Bourse
A1: 📈 PORTEFEUILLE BOURSE
A3: 💵 VERSEMENTS MENSUELS
A4: Mois | B4: Versement Prévu | C4: Versement Effectué | D4: Versement Extra | E4: TOTAL
A5: Janvier 2025 | B5: 1000 | C5: 1000 | D5: 0 | E5: =C5+D5
A6: Février 2025 | B6: 1000 | C6: 1000 | D6: 0 | E6: =C6+D6
A7: Mars 2025 | B7: 1000 | C7: 1000 | D7: 0 | E7: =C7+D7
A8: TOTAL INVESTI | B8: =SUM(B5:B7) | C8: =SUM(C5:C7) | D8: =SUM(D5:D7) | E8: =SUM(E5:E7)
A11: 📊 PORTEFEUILLE D'ACTIONS/ETF
A12: Date Achat | B12: Ticker/Nom | C12: Secteur | D12: Quantité | E12: Prix Achat | F12: Valeur Achat | G12: Prix Actuel | H12: Valeur Actuelle | I12: +/- Value | J12: % Gain/Perte
A13: 15/01/2025 | B13: EXEMPLE ETF | C13: Indices | D13: 10 | E13: 100 | F13: =D13*E13 | G13: 105 | H13: =D13*G13 | I13: =H13-F13 | J13: =I13/F13
A14: 20/01/2025 | B14: EXEMPLE ACTION | C14: Tech | D14: 5 | E14: 200 | F14: =D14*E14 | G14: 210 | H14: =D14*G14 | I14: =H14-F14 | J14: =I14/F14
A15: TOTAL PORTEFEUILLE | F15: =SUM(F13:F14) | H15: =SUM(H13:H14) | I15: =SUM(I13:I14) | J15: =I15/F15
A18: 📈 PERFORMANCE DU PORTEFEUILLE
A19: Valeur totale investie: | B19: =F15 | D19: 💰 DIVIDENDES REÇUS
A20: Valeur actuelle: | B20: =H15 | D20: Date | E20: Ticker | F20: Montant
A21: Gain/Perte total: | B21: =I15
A22: Performance (%): | B22: =J15

Sheet Patrimoine Global
A1: 💎 PATRIMOINE GLOBAL
A3: Mois | B3: Épargne Personnelle | C3: Épargne Famille | D3: Portefeuille Bourse | E3: TOTAL PATRIMOINE | F3: Variation
A4: Janvier 2025 | B4: =Épargne!E6 | C4: =Épargne!C22 | D4: ='Investissements Bourse'!H15 | E4: =B4+C4+D4 | F4: 0
A5: Février 2025 | B5: =Épargne!E7 | C5: =Épargne!C23 | D5: ='Investissements Bourse'!H15 | E5: =B5+C5+D5 | F5: =E5-E4
A6: Mars 2025 | B6: =Épargne!E8 | C6: =Épargne!C24 | D6: ='Investissements Bourse'!H15 | E6: =B6+C6+D6 | F6: =E6-E5
A7: Mois 4 | B7: 0 | C7: 0 | D7: 0 | E7: =B7+C7+D7 | F7: =E7-E6
A8: Mois 5 | B8: 0 | C8: 0 | D8: 0 | E8: =B8+C8+D8 | F8: =E8-E7
A9: Mois 6 | B9: 0 | C9: 0 | D9: 0 | E9: =B9+C9+D9 | F9: =E9-E8
A10: Mois 7 | B10: 0 | C10: 0 | D10: 0 | E10: =B10+C10+D10 | F10: =E10-E9
A11: Mois 8 | B11: 0 | C11: 0 | D11: 0 | E11: =B11+C11+D11 | F11: =E11-E10
A12: Mois 9 | B12: 0 | C12: 0 | D12: 0 | E12: =B12+C12+D12 | F12: =E12-E11
A13: Mois 10 | B13: 0 | C13: 0 | D13: 0 | E13: =B13+C13+D13 | F13: =E13-E12
A14: Mois 11 | B14: 0 | C14: 0 | D14: 0 | E14: =B14+C14+D14 | F14: =E14-E13
A15: Mois 12 | B15: 0 | C15: 0 | D15: 0 | E15: =B15+C15+D15 | F15: =E15-E14
A18: 📊 STATISTIQUES
A19: Patrimoine actuel: | B19: =E6
A20: Croissance moyenne/mois: | B20: =AVERAGE(F4:F6)
A21: Objectif fin 2025: | B21: =E6+9*((B6-B4)/2+(C6-C4)/2+1000)
A22: Mois d'épargne d'urgence: | B22: =E6/14000
